mora/__init__.py
mora/bot.py
mora/command_exec.py
mora/file_ops.py
mora/handlers.py
mora/sys_info.py
mora-0.2.0.dist-info/licenses/LICENSE
mora-0.2.0.dist-info/METADATA
mora-0.2.0.dist-info/WHEEL
mora-0.2.0.dist-info/top_level.txt
mora-0.2.0.dist-info/RECORD
